mockselector/__init__.py
mockselector/selector.py
mockselector/version.py
mockselector-0.2.3.dist-info/LICENCE.txt
mockselector-0.2.3.dist-info/METADATA
mockselector-0.2.3.dist-info/WHEEL
mockselector-0.2.3.dist-info/top_level.txt
mockselector-0.2.3.dist-info/RECORD
