Metadata-Version: 2.1
Name: mockselector
Version: 0.2.3
Summary: Mock subclass of BaseSelector
Home-page: https://github.com/s-ball/MockSelector
Author: SBA
Author-email: s-ball@laposte.net
License: MIT
Platform: UNKNOWN
Classifier: Development Status :: 4 - Beta
Classifier: Intended Audience :: Developers
Classifier: Topic :: Software Development :: Testing :: Mocking
Classifier: License :: OSI Approved :: MIT License
Classifier: Programming Language :: Python :: 3
Classifier: Programming Language :: Python :: 3.5
Classifier: Programming Language :: Python :: 3.6
Classifier: Programming Language :: Python :: 3.7
Classifier: Programming Language :: Python :: 3.8
Requires-Python: >=3.5
